pyscreeze-stubs/METADATA.toml
pyscreeze-stubs/__init__.pyi
pyscreeze-stubs/py.typed
types_pyscreeze-1.0.1.20250425.dist-info/licenses/LICENSE
types_pyscreeze-1.0.1.20250425.dist-info/METADATA
types_pyscreeze-1.0.1.20250425.dist-info/WHEEL
types_pyscreeze-1.0.1.20250425.dist-info/top_level.txt
types_pyscreeze-1.0.1.20250425.dist-info/RECORD
